{
  "usableSessionsCount": 12,
  "retiredSessionsCount": 0,
  "sessions": [
    {
      "id": "session_i7H9P8QaqL",
      "cookieJar": {
        "version": "tough-cookie@5.1.2",
        "storeType": "MemoryCookieStore",
        "rejectPublicSuffixes": true,
        "enableLooseMode": false,
        "allowSpecialUseDomain": true,
        "prefixSecurity": "silent",
        "cookies": []
      },
      "userData": {},
      "maxErrorScore": 3,
      "errorScoreDecrement": 0.5,
      "expiresAt": "2025-04-12T23:09:29.891Z",
      "createdAt": "2025-04-12T22:19:29.891Z",
      "usageCount": 0,
      "maxUsageCount": 50,
      "errorScore": 0
    },
    {
      "id": "session_BzQD1YhSpz",
      "cookieJar": {
        "version": "tough-cookie@5.1.2",
        "storeType": "MemoryCookieStore",
        "rejectPublicSuffixes": true,
        "enableLooseMode": false,
        "allowSpecialUseDomain": true,
        "prefixSecurity": "silent",
        "cookies": []
      },
      "userData": {},
      "maxErrorScore": 3,
      "errorScoreDecrement": 0.5,
      "expiresAt": "2025-04-12T23:09:29.894Z",
      "createdAt": "2025-04-12T22:19:29.894Z",
      "usageCount": 11,
      "maxUsageCount": 50,
      "errorScore": 0
    },
    {
      "id": "session_plMIZbid2G",
      "cookieJar": {
        "version": "tough-cookie@5.1.2",
        "storeType": "MemoryCookieStore",
        "rejectPublicSuffixes": true,
        "enableLooseMode": false,
        "allowSpecialUseDomain": true,
        "prefixSecurity": "silent",
        "cookies": []
      },
      "userData": {},
      "maxErrorScore": 3,
      "errorScoreDecrement": 0.5,
      "expiresAt": "2025-04-12T23:09:31.102Z",
      "createdAt": "2025-04-12T22:19:31.102Z",
      "usageCount": 0,
      "maxUsageCount": 50,
      "errorScore": 0
    },
    {
      "id": "session_wRUROPWeCt",
      "cookieJar": {
        "version": "tough-cookie@5.1.2",
        "storeType": "MemoryCookieStore",
        "rejectPublicSuffixes": true,
        "enableLooseMode": false,
        "allowSpecialUseDomain": true,
        "prefixSecurity": "silent",
        "cookies": []
      },
      "userData": {},
      "maxErrorScore": 3,
      "errorScoreDecrement": 0.5,
      "expiresAt": "2025-04-12T23:09:31.103Z",
      "createdAt": "2025-04-12T22:19:31.103Z",
      "usageCount": 0,
      "maxUsageCount": 50,
      "errorScore": 0
    },
    {
      "id": "session_mclmHa8zFY",
      "cookieJar": {
        "version": "tough-cookie@5.1.2",
        "storeType": "MemoryCookieStore",
        "rejectPublicSuffixes": true,
        "enableLooseMode": false,
        "allowSpecialUseDomain": true,
        "prefixSecurity": "silent",
        "cookies": []
      },
      "userData": {},
      "maxErrorScore": 3,
      "errorScoreDecrement": 0.5,
      "expiresAt": "2025-04-12T23:09:31.732Z",
      "createdAt": "2025-04-12T22:19:31.732Z",
      "usageCount": 0,
      "maxUsageCount": 50,
      "errorScore": 0
    },
    {
      "id": "session_0fbmaXl2Oe",
      "cookieJar": {
        "version": "tough-cookie@5.1.2",
        "storeType": "MemoryCookieStore",
        "rejectPublicSuffixes": true,
        "enableLooseMode": false,
        "allowSpecialUseDomain": true,
        "prefixSecurity": "silent",
        "cookies": []
      },
      "userData": {},
      "maxErrorScore": 3,
      "errorScoreDecrement": 0.5,
      "expiresAt": "2025-04-12T23:09:31.747Z",
      "createdAt": "2025-04-12T22:19:31.747Z",
      "usageCount": 0,
      "maxUsageCount": 50,
      "errorScore": 0
    },
    {
      "id": "session_a0kJqqVFch",
      "cookieJar": {
        "version": "tough-cookie@5.1.2",
        "storeType": "MemoryCookieStore",
        "rejectPublicSuffixes": true,
        "enableLooseMode": false,
        "allowSpecialUseDomain": true,
        "prefixSecurity": "silent",
        "cookies": []
      },
      "userData": {},
      "maxErrorScore": 3,
      "errorScoreDecrement": 0.5,
      "expiresAt": "2025-04-12T23:09:32.079Z",
      "createdAt": "2025-04-12T22:19:32.079Z",
      "usageCount": 0,
      "maxUsageCount": 50,
      "errorScore": 0
    },
    {
      "id": "session_groSpFGhdZ",
      "cookieJar": {
        "version": "tough-cookie@5.1.2",
        "storeType": "MemoryCookieStore",
        "rejectPublicSuffixes": true,
        "enableLooseMode": false,
        "allowSpecialUseDomain": true,
        "prefixSecurity": "silent",
        "cookies": []
      },
      "userData": {},
      "maxErrorScore": 3,
      "errorScoreDecrement": 0.5,
      "expiresAt": "2025-04-12T23:09:32.109Z",
      "createdAt": "2025-04-12T22:19:32.109Z",
      "usageCount": 0,
      "maxUsageCount": 50,
      "errorScore": 0
    },
    {
      "id": "session_ezUc6lC6jx",
      "cookieJar": {
        "version": "tough-cookie@5.1.2",
        "storeType": "MemoryCookieStore",
        "rejectPublicSuffixes": true,
        "enableLooseMode": false,
        "allowSpecialUseDomain": true,
        "prefixSecurity": "silent",
        "cookies": []
      },
      "userData": {},
      "maxErrorScore": 3,
      "errorScoreDecrement": 0.5,
      "expiresAt": "2025-04-12T23:09:32.382Z",
      "createdAt": "2025-04-12T22:19:32.382Z",
      "usageCount": 0,
      "maxUsageCount": 50,
      "errorScore": 0
    },
    {
      "id": "session_MBMukmBacb",
      "cookieJar": {
        "version": "tough-cookie@5.1.2",
        "storeType": "MemoryCookieStore",
        "rejectPublicSuffixes": true,
        "enableLooseMode": false,
        "allowSpecialUseDomain": true,
        "prefixSecurity": "silent",
        "cookies": []
      },
      "userData": {},
      "maxErrorScore": 3,
      "errorScoreDecrement": 0.5,
      "expiresAt": "2025-04-12T23:09:32.397Z",
      "createdAt": "2025-04-12T22:19:32.397Z",
      "usageCount": 0,
      "maxUsageCount": 50,
      "errorScore": 0
    },
    {
      "id": "session_yqARXi9whq",
      "cookieJar": {
        "version": "tough-cookie@5.1.2",
        "storeType": "MemoryCookieStore",
        "rejectPublicSuffixes": true,
        "enableLooseMode": false,
        "allowSpecialUseDomain": true,
        "prefixSecurity": "silent",
        "cookies": []
      },
      "userData": {},
      "maxErrorScore": 3,
      "errorScoreDecrement": 0.5,
      "expiresAt": "2025-04-12T23:09:32.794Z",
      "createdAt": "2025-04-12T22:19:32.794Z",
      "usageCount": 0,
      "maxUsageCount": 50,
      "errorScore": 0
    },
    {
      "id": "session_H9P7ebshFX",
      "cookieJar": {
        "version": "tough-cookie@5.1.2",
        "storeType": "MemoryCookieStore",
        "rejectPublicSuffixes": true,
        "enableLooseMode": false,
        "allowSpecialUseDomain": true,
        "prefixSecurity": "silent",
        "cookies": []
      },
      "userData": {},
      "maxErrorScore": 3,
      "errorScoreDecrement": 0.5,
      "expiresAt": "2025-04-12T23:09:32.893Z",
      "createdAt": "2025-04-12T22:19:32.893Z",
      "usageCount": 0,
      "maxUsageCount": 50,
      "errorScore": 0
    }
  ]
}