{
	"id": "DPwNZ5Yad75DZNx",
	"json": "{\"id\":\"DPwNZ5Yad75DZNx\",\"url\":\"https://playwright.dev/python/docs/api/class-jshandle\",\"uniqueKey\":\"https://playwright.dev/python/docs/api/class-jshandle\",\"method\":\"GET\",\"noRetry\":false,\"retryCount\":0,\"errorMessages\":[],\"headers\":{},\"userData\":{\"__crawlee\":{\"enqueueStrategy\":\"same-hostname\"}}}",
	"method": "GET",
	"orderNo": 1744467809085,
	"retryCount": 0,
	"uniqueKey": "https://playwright.dev/python/docs/api/class-jshandle",
	"url": "https://playwright.dev/python/docs/api/class-jshandle"
}