{
	"id": "l5V2SmKQLW770bo",
	"json": "{\"id\":\"l5V2SmKQLW770bo\",\"url\":\"https://playwright.dev/dotnet/docs/api/class-apirequest\",\"uniqueKey\":\"https://playwright.dev/dotnet/docs/api/class-apirequest\",\"method\":\"GET\",\"noRetry\":false,\"retryCount\":0,\"errorMessages\":[],\"headers\":{},\"userData\":{\"__crawlee\":{\"enqueueStrategy\":\"same-hostname\"}}}",
	"method": "GET",
	"orderNo": 1744467811291,
	"retryCount": 0,
	"uniqueKey": "https://playwright.dev/dotnet/docs/api/class-apirequest",
	"url": "https://playwright.dev/dotnet/docs/api/class-apirequest"
}